odoo/addons/l10n_it_fatturapa_out_dn/README.rst
odoo/addons/l10n_it_fatturapa_out_dn/__init__.py
odoo/addons/l10n_it_fatturapa_out_dn/__manifest__.py
odoo/addons/l10n_it_fatturapa_out_dn/data/invoice_it_template.xml
odoo/addons/l10n_it_fatturapa_out_dn/i18n/l10n_it_fatturapa_out_dn.pot
odoo/addons/l10n_it_fatturapa_out_dn/readme/CONTRIBUTORS.rst
odoo/addons/l10n_it_fatturapa_out_dn/readme/DESCRIPTION.rst
odoo/addons/l10n_it_fatturapa_out_dn/readme/ROADMAP.rst
odoo/addons/l10n_it_fatturapa_out_dn/security/ir.model.access.csv
odoo/addons/l10n_it_fatturapa_out_dn/static/description/icon.png
odoo/addons/l10n_it_fatturapa_out_dn/static/description/index.html
odoo/addons/l10n_it_fatturapa_out_dn/tests/__init__.py
odoo/addons/l10n_it_fatturapa_out_dn/tests/test_l10n_it_fatturapa_out_dn.py
odoo/addons/l10n_it_fatturapa_out_dn/tests/data/IT06363391001_outDDT.xml
odoo/addons/l10n_it_fatturapa_out_dn/wizard/__init__.py
odoo/addons/l10n_it_fatturapa_out_dn/wizard/wizard_export_fatturapa.py
odoo/addons/l10n_it_fatturapa_out_dn/wizard/wizard_export_fatturapa_view.xml
odoo14_addon_l10n_it_fatturapa_out_dn-14.0.1.1.0.dist-info/METADATA
odoo14_addon_l10n_it_fatturapa_out_dn-14.0.1.1.0.dist-info/WHEEL
odoo14_addon_l10n_it_fatturapa_out_dn-14.0.1.1.0.dist-info/top_level.txt
odoo14_addon_l10n_it_fatturapa_out_dn-14.0.1.1.0.dist-info/RECORD
